.travis.yml
CHANGELOG.rst
LICENSE
MANIFEST.in
README.rst
dev-requirements.txt
setup.py
tox.ini
kinto_migrations/__init__.py
kinto_migrations/__main__.py
kinto_migrations.egg-info/PKG-INFO
kinto_migrations.egg-info/SOURCES.txt
kinto_migrations.egg-info/dependency_links.txt
kinto_migrations.egg-info/entry_points.txt
kinto_migrations.egg-info/not-zip-safe
kinto_migrations.egg-info/requires.txt
kinto_migrations.egg-info/top_level.txt
tests/__init__.py
tests/test_migrations.py