Metadata-Version: 1.1
Name: kinto-migrations
Version: 0.1.0
Summary: Run Kinto HTTP migrations.
Home-page: https://github.com/gabisurita/kinto-migrations
Author: Gabriela Suria
Author-email: gabsurita@gmail.com
License: Apache License (2.0)
Keywords: kinto
Platform: UNKNOWN
Classifier: Development Status :: 2 - Pre-Alpha
Classifier: Intended Audience :: Developers
Classifier: License :: OSI Approved :: Apache Software License
Classifier: Natural Language :: English
Classifier: Programming Language :: Python :: 2
Classifier: Programming Language :: Python :: 2.7
Classifier: Programming Language :: Python :: 3
Classifier: Programming Language :: Python :: 3.4
